pykoi/__init__.py
pykoi/application.py
pykoi/chat/__init__.py
pykoi/chat/db/__init__.py
pykoi/chat/db/abs_database.py
pykoi/chat/db/comparator_database.py
pykoi/chat/db/constants.py
pykoi/chat/db/qa_database.py
pykoi/chat/db/rag_database.py
pykoi/chat/db/ranking_database.py
pykoi/chat/llm/__init__.py
pykoi/chat/llm/abs_llm.py
pykoi/chat/llm/constants.py
pykoi/chat/llm/huggingface.py
pykoi/chat/llm/instruct_pipeline.py
pykoi/chat/llm/mlu.py
pykoi/chat/llm/model_factory.py
pykoi/chat/llm/openai.py
pykoi/chat/llm/peft_huggingface.py
pykoi/component/__init__.py
pykoi/component/base.py
pykoi/component/chatbot_comparator.py
pykoi/component/chatbot_database_factory.py
pykoi/component/constants.py
pykoi/component/nvml.py
pykoi/component/retrieval_qa.py
pykoi/frontend/.gitignore
pykoi/frontend/README.md
pykoi/frontend/dist/assets/index-33aea1b9.css
pykoi/frontend/dist/assets/index-8dfc5bce.js
pykoi/frontend/dist/index.html
pykoi/frontend/dist/vite.svg
pykoi/frontend/index.html
pykoi/frontend/jsconfig.json
pykoi/frontend/package.json
pykoi/frontend/public/vite.svg
pykoi/frontend/src/App.svelte
pykoi/frontend/src/app.css
pykoi/frontend/src/assets/CloudArrowUp.svelte
pykoi/frontend/src/assets/svelte.svg
pykoi/frontend/src/lib/Annotations/QuestionRating.svelte
pykoi/frontend/src/lib/Chatbots/Chat.svelte
pykoi/frontend/src/lib/Chatbots/Chatbot.svelte
pykoi/frontend/src/lib/Chatbots/ComparisonChat.svelte
pykoi/frontend/src/lib/Chatbots/Components/Answer.svelte
pykoi/frontend/src/lib/Chatbots/Components/DownloadModal.svelte
pykoi/frontend/src/lib/Chatbots/Components/Dropdown.svelte
pykoi/frontend/src/lib/Chatbots/Components/ModifiedAnswer.svelte
pykoi/frontend/src/lib/Chatbots/Components/SourceContainer.svelte
pykoi/frontend/src/lib/Chatbots/Components/SourceRow.svelte
pykoi/frontend/src/lib/Chatbots/RAGChatbot.svelte
pykoi/frontend/src/lib/Chatbots/RankChatComparison.svelte
pykoi/frontend/src/lib/Chatbots/RankChatbotOld.svelte
pykoi/frontend/src/lib/Chatbots/RankedChatbot.svelte
pykoi-0.0.11.dist-info/LICENSE.txt
pykoi-0.0.11.dist-info/METADATA
pykoi-0.0.11.dist-info/WHEEL
pykoi-0.0.11.dist-info/RECORD
