Metadata-Version: 2.1
Name: pykoi
Version: 0.0.11
Summary: pykoi: Active learning in one unified interface
License: Apache
Author: CambioML
Author-email: wanwanaiai45@gmail.com
Requires-Python: >=3.9,<3.13
Classifier: License :: Other/Proprietary License
Classifier: Programming Language :: Python :: 3
Classifier: Programming Language :: Python :: 3.9
Classifier: Programming Language :: Python :: 3.10
Classifier: Programming Language :: Python :: 3.11
Provides-Extra: huggingface
Provides-Extra: rag
Provides-Extra: rlhf
Requires-Dist: accelerate (==0.21.0) ; extra == "huggingface" or extra == "rlhf"
Requires-Dist: bcrypt (==4.0.1)
Requires-Dist: bitsandbytes (==0.40.2) ; extra == "huggingface" or extra == "rlhf"
Requires-Dist: chromadb (==0.4.20) ; extra == "rag"
Requires-Dist: datasets (==2.15.0) ; extra == "rlhf"
Requires-Dist: docx2txt (==0.8) ; extra == "rag"
Requires-Dist: einops (==0.6.1) ; extra == "huggingface" or extra == "rlhf"
Requires-Dist: evaluate (==0.4.0) ; extra == "rlhf"
Requires-Dist: fastapi (==0.100.0)
Requires-Dist: langchain (==0.0.338) ; extra == "rag"
Requires-Dist: openai (==1.6.1)
Requires-Dist: packaging (==23.1)
Requires-Dist: pandas (==2.0.3)
Requires-Dist: passlib (==1.7.4)
Requires-Dist: pdfminer-six (==20221105) ; extra == "rag"
Requires-Dist: peft (==0.7.1) ; extra == "rlhf"
Requires-Dist: posthog (==3.0.1)
Requires-Dist: pydantic (==2.5.2)
Requires-Dist: pyepsilla (>=0.1.1) ; extra == "rag"
Requires-Dist: pynvml (==11.5.0)
Requires-Dist: python-dotenv (>=1.0.0,<2.0.0)
Requires-Dist: python-multipart (==0.0.6) ; extra == "rag"
Requires-Dist: scikit-learn (==1.3.0) ; extra == "rag" or extra == "rlhf"
Requires-Dist: scipy (==1.11.1)
Requires-Dist: sentence-transformers (==2.2.2) ; extra == "huggingface"
Requires-Dist: starlette (==0.27.0)
Requires-Dist: tiktoken (==0.4.0) ; extra == "rag"
Requires-Dist: transformers (==4.36.2) ; extra == "huggingface" or extra == "rlhf"
Requires-Dist: trl (==0.7.4) ; extra == "rlhf"
Requires-Dist: uvicorn (==0.23.1)
